alnvu/__init__.py
alnvu/av.py
alnvu/html.py
alnvu/pdf.py
alnvu/util.py
alnvu/data/__init__.py
alnvu/data/html_template.jinja
alnvu/data/na_colors.csv
alnvu/data/readme.txt
alnvu/data/ver
alnvu-0.2.dist-info/DESCRIPTION.rst
alnvu-0.2.dist-info/METADATA
alnvu-0.2.dist-info/RECORD
alnvu-0.2.dist-info/WHEEL
alnvu-0.2.dist-info/entry_points.txt
alnvu-0.2.dist-info/metadata.json
alnvu-0.2.dist-info/top_level.txt
