Metadata-Version: 2.0
Name: alnvu
Version: 0.2
Summary: Reformat and condense multiple sequence alignments to highlight variability
Home-page: http://github.com/nhoffman/alnvu
Author: Noah Hoffman
Author-email: noah.hoffman@gmail.com
License: UNKNOWN
Platform: UNKNOWN
Requires: python (>= 2.7)
Requires-Dist: Jinja2 (>=2.7)
Requires-Dist: colorbrewer (>=0.1.1)
Requires-Dist: reportlab (>=3.0)
